src/__init__.py
src/fhir_load.py
src/database/__init__.py
src/database/create_database.py
src/database/database_functions/__init__.py
src/database/database_functions/database_connection.py
src/database/database_sql/__init__.py
src/database/database_sql/database.py
src/database/database_sql/tables.py
src/etl/__init__.py
src/etl/pipeline.py
src/etl/pipeline_functions/__init__.py
src/etl/pipeline_functions/extract.py
src/etl/pipeline_functions/load.py
src/etl/pipeline_functions/transform.py
src/etl/resources/__init__.py
src/etl/resources/schemas.py
fhir_load-1.5.dist-info/METADATA
fhir_load-1.5.dist-info/WHEEL
fhir_load-1.5.dist-info/entry_points.txt
fhir_load-1.5.dist-info/top_level.txt
fhir_load-1.5.dist-info/RECORD
