Metadata-Version: 2.1
Name: fhir-load
Version: 1.5
Summary: This program loads FHIR Transaction Bundle data to resource tables in a postgreSQL database called fhir_database.
License: UNKNOWN
Platform: UNKNOWN
Requires-Dist: psycopg2 (==2.9.5)
